wsp/__init__.py
wsp/client.py
wsp-0.0.1.dist-info/licenses/LICENSE
wsp-0.0.1.dist-info/METADATA
wsp-0.0.1.dist-info/WHEEL
wsp-0.0.1.dist-info/top_level.txt
wsp-0.0.1.dist-info/RECORD
