Metadata-Version: 2.4
Name: wsp
Version: 0.0.1
Summary: Whatsapp Business API Python Package
Home-page: https://pypi.org/project/wsp/
Author: Alejo Prieto Dávalos
Author-email: alejoprietodavalos@gmail.com
Project-URL: Source, https://github.com/AlejoPrietoDavalos/wsp/
Requires-Python: >=3.11
License-File: LICENSE
Requires-Dist: requests>=2.32
Dynamic: author
Dynamic: author-email
Dynamic: description
Dynamic: description-content-type
Dynamic: home-page
Dynamic: license-file
Dynamic: project-url
Dynamic: requires-dist
Dynamic: requires-python
Dynamic: summary
